hdd_time_server.py
hdd_mcp_time-0.1.0.dist-info/METADATA
hdd_mcp_time-0.1.0.dist-info/WHEEL
hdd_mcp_time-0.1.0.dist-info/entry_points.txt
hdd_mcp_time-0.1.0.dist-info/top_level.txt
hdd_mcp_time-0.1.0.dist-info/RECORD
