Metadata-Version: 2.4
Name: hdd-mcp-time
Version: 0.1.0
Summary: its time
Requires-Python: >=3.12
Requires-Dist: fastmcp>=2.12.4
